kaf_retry_wrapper/__init__.py
kaf_retry_wrapper/kafka_consumer.py
kaf_retry_wrapper/kafka_producer.py
kaf_retry_wrapper-0.1.2.dist-info/licenses/LICENSE
kaf_retry_wrapper-0.1.2.dist-info/METADATA
kaf_retry_wrapper-0.1.2.dist-info/WHEEL
kaf_retry_wrapper-0.1.2.dist-info/top_level.txt
kaf_retry_wrapper-0.1.2.dist-info/RECORD
